gxlogger/__init__.py
gxlogger/logger.py
gxlogger-0.1.4.dist-info/METADATA
gxlogger-0.1.4.dist-info/WHEEL
gxlogger-0.1.4.dist-info/top_level.txt
gxlogger-0.1.4.dist-info/RECORD
