Metadata-Version: 2.1
Name: gxlogger
Version: 0.1.4
Summary: Logger for myself.
Home-page: UNKNOWN
Author: gawainx
Author-email: liangyi@bupt.edu.cn
License: UNKNOWN
Platform: UNKNOWN
Classifier: Programming Language :: Python :: 3.7
Classifier: License :: OSI Approved :: MIT License
Classifier: Operating System :: OS Independent
